lastplot/__init__.py
lastplot/computing_statistics.py
lastplot/data_cleanup.py
lastplot/graph_constructor.py
lastplot/log10_graphs.py
lastplot/saving.py
lastplot/workflows.py
lastplot/zscores_graphs.py
lastplot-1.2.1.dist-info/LICENSE
lastplot-1.2.1.dist-info/WHEEL
lastplot-1.2.1.dist-info/METADATA
lastplot-1.2.1.dist-info/RECORD
