Metadata-Version: 2.1
Name: lastplot
Version: 1.2.1
Summary: LastPlot is a Python package designed to elaborate data into graphs coming from lipid extractions (LC/MS).
Author-email: Elide Brunelli <elide.98@gmail.com>
Classifier: License :: OSI Approved :: MIT License
Requires-Dist: numpy~=2.0
Requires-Dist: pandas~=2.0
Requires-Dist: openpyxl~=3.1
Requires-Dist: scipy~=1.13
Requires-Dist: matplotlib~=3.9
Requires-Dist: seaborn~=0.13
Requires-Dist: starbars~=1.1
Requires-Dist: rich~=13.0
Requires-Dist: sphinx-book-theme ; extra == "docs"
Project-URL: Home, https://github.com/elide-b/lastplot
Provides-Extra: docs
